{
  "458": {
    "ward_no": "CANT_1",
    "drain_capacity": 124,
    "imperviousness": 0.943,
    "area": 10000.0,
    "elevation": "High-Density"
  },
  "890": {
    "ward_no": "CANT_2",
    "drain_capacity": 50,
    "imperviousness": 0.966,
    "area": 10000.0,
    "elevation": "Low"
  },
  "103": {
    "ward_no": "CANT_4",
    "drain_capacity": 178,
    "imperviousness": 0.98,
    "area": 10000.0,
    "elevation": "Low"
  },
  "37": {
    "ward_no": "CANT_5",
    "drain_capacity": 70,
    "imperviousness": 0.924,
    "area": 10000.0,
    "elevation": "Low"
  },
  "67": {
    "ward_no": "CANT_6",
    "drain_capacity": 112,
    "imperviousness": 0.854,
    "area": 10000.0,
    "elevation": "Moderate"
  },
  "282": {
    "ward_no": "CANT_7",
    "drain_capacity": 140,
    "imperviousness": 0.874,
    "area": 10000.0,
    "elevation": "Low"
  },
  "139": {
    "ward_no": "CANT_8",
    "drain_capacity": 54,
    "imperviousness": 0.879,
    "area": 10000.0,
    "elevation": "Moderate"
  },
  "390": {
    "ward_no": "CANT_3",
    "drain_capacity": 68,
    "imperviousness": 0.98,
    "area": 10000.0,
    "elevation": "High-Density"
  },
  "689": {
    "ward_no": "NDMC_1",
    "drain_capacity": 72,
    "imperviousness": 0.956,
    "area": 10000.0,
    "elevation": "High-Density"
  },
  "402": {
    "ward_no": "NDMC_2",
    "drain_capacity": 69,
    "imperviousness": 0.98,
    "area": 10000.0,
    "elevation": "Low"
  },
  "736": {
    "ward_no": "NDMC_3",
    "drain_capacity": 69,
    "imperviousness": 0.98,
    "area": 10000.0,
    "elevation": "Low"
  },
  "399": {
    "ward_no": "NDMC_4",
    "drain_capacity": 73,
    "imperviousness": 0.95,
    "area": 10000.0,
    "elevation": "Sink"
  },
  "912": {
    "ward_no": "NDMC_5",
    "drain_capacity": 141,
    "imperviousness": 0.889,
    "area": 10000.0,
    "elevation": "Moderate"
  },
  "592": {
    "ward_no": "128",
    "drain_capacity": 58,
    "imperviousness": 0.92,
    "area": 10000.0,
    "elevation": "Moderate"
  },
  "862": {
    "ward_no": "158",
    "drain_capacity": 82,
    "imperviousness": 0.939,
    "area": 10000.0,
    "elevation": "Low"
  },
  "829": {
    "ward_no": "NDMC_9",
    "drain_capacity": 50,
    "imperviousness": 0.871,
    "area": 10000.0,
    "elevation": "Low"
  },
  "579": {
    "ward_no": "NDMC_6",
    "drain_capacity": 76,
    "imperviousness": 0.98,
    "area": 10000.0,
    "elevation": "Low"
  },
  "718": {
    "ward_no": "80",
    "drain_capacity": 50,
    "imperviousness": 0.957,
    "area": 10000.0,
    "elevation": "Sink"
  },
  "879": {
    "ward_no": "81",
    "drain_capacity": 66,
    "imperviousness": 0.98,
    "area": 10000.0,
    "elevation": "Low"
  },
  "169": {
    "ward_no": "172",
    "drain_capacity": 162,
    "imperviousness": 0.846,
    "area": 10000.0,
    "elevation": "Low"
  },
  "201": {
    "ward_no": "83",
    "drain_capacity": 58,
    "imperviousness": 0.935,
    "area": 10000.0,
    "elevation": "Sink"
  },
  "310": {
    "ward_no": "85",
    "drain_capacity": 50,
    "imperviousness": 0.98,
    "area": 10000.0,
    "elevation": "Low"
  },
  "653": {
    "ward_no": "108",
    "drain_capacity": 50,
    "imperviousness": 0.89,
    "area": 10000.0,
    "elevation": "High-Density"
  },
  "863": {
    "ward_no": "109",
    "drain_capacity": 141,
    "imperviousness": 0.965,
    "area": 10000.0,
    "elevation": "Moderate"
  },
  "380": {
    "ward_no": "11",
    "drain_capacity": 118,
    "imperviousness": 0.918,
    "area": 10000.0,
    "elevation": "High-Density"
  },
  "409": {
    "ward_no": "117",
    "drain_capacity": 174,
    "imperviousness": 0.967,
    "area": 10000.0,
    "elevation": "Moderate"
  },
  "126": {
    "ward_no": "118",
    "drain_capacity": 50,
    "imperviousness": 0.98,
    "area": 10000.0,
    "elevation": "Low"
  },
  "900": {
    "ward_no": "119",
    "drain_capacity": 50,
    "imperviousness": 0.98,
    "area": 10000.0,
    "elevation": "High-Density"
  },
  "623": {
    "ward_no": "120",
    "drain_capacity": 89,
    "imperviousness": 0.968,
    "area": 10000.0,
    "elevation": "Moderate"
  },
  "907": {
    "ward_no": "259",
    "drain_capacity": 104,
    "imperviousness": 0.925,
    "area": 10000.0,
    "elevation": "High-Density"
  },
  "393": {
    "ward_no": "266",
    "drain_capacity": 83,
    "imperviousness": 0.94,
    "area": 10000.0,
    "elevation": "Sink"
  },
  "25": {
    "ward_no": "135",
    "drain_capacity": 125,
    "imperviousness": 0.98,
    "area": 10000.0,
    "elevation": "Sink"
  },
  "459": {
    "ward_no": "47",
    "drain_capacity": 94,
    "imperviousness": 0.958,
    "area": 10000.0,
    "elevation": "Low"
  },
  "85": {
    "ward_no": "241",
    "drain_capacity": 168,
    "imperviousness": 0.959,
    "area": 10000.0,
    "elevation": "Sink"
  },
  "290": {
    "ward_no": "242",
    "drain_capacity": 64,
    "imperviousness": 0.934,
    "area": 10000.0,
    "elevation": "Low"
  },
  "810": {
    "ward_no": "113",
    "drain_capacity": 50,
    "imperviousness": 0.98,
    "area": 10000.0,
    "elevation": "High-Density"
  },
  "69": {
    "ward_no": "244",
    "drain_capacity": 100,
    "imperviousness": 0.938,
    "area": 10000.0,
    "elevation": "Moderate"
  },
  "525": {
    "ward_no": "245",
    "drain_capacity": 80,
    "imperviousness": 0.936,
    "area": 10000.0,
    "elevation": "Moderate"
  },
  "124": {
    "ward_no": "246",
    "drain_capacity": 91,
    "imperviousness": 0.97,
    "area": 10000.0,
    "elevation": "High-Density"
  },
  "432": {
    "ward_no": "247",
    "drain_capacity": 52,
    "imperviousness": 0.98,
    "area": 10000.0,
    "elevation": "Sink"
  },
  "964": {
    "ward_no": "248",
    "drain_capacity": 50,
    "imperviousness": 0.949,
    "area": 10000.0,
    "elevation": "Low"
  },
  "229": {
    "ward_no": "249",
    "drain_capacity": 105,
    "imperviousness": 0.928,
    "area": 10000.0,
    "elevation": "High-Density"
  },
  "235": {
    "ward_no": "262",
    "drain_capacity": 131,
    "imperviousness": 0.942,
    "area": 10000.0,
    "elevation": "Low"
  },
  "675": {
    "ward_no": "252",
    "drain_capacity": 116,
    "imperviousness": 0.95,
    "area": 10000.0,
    "elevation": "Low"
  },
  "291": {
    "ward_no": "255",
    "drain_capacity": 157,
    "imperviousness": 0.98,
    "area": 10000.0,
    "elevation": "Low"
  },
  "764": {
    "ward_no": "256",
    "drain_capacity": 59,
    "imperviousness": 0.98,
    "area": 10000.0,
    "elevation": "High-Density"
  },
  "856": {
    "ward_no": "45",
    "drain_capacity": 63,
    "imperviousness": 0.979,
    "area": 10000.0,
    "elevation": "Low"
  },
  "267": {
    "ward_no": "258",
    "drain_capacity": 75,
    "imperviousness": 0.98,
    "area": 10000.0,
    "elevation": "Low"
  },
  "92": {
    "ward_no": "92",
    "drain_capacity": 118,
    "imperviousness": 0.92,
    "area": 10000.0,
    "elevation": "Sink"
  },
  "294": {
    "ward_no": "261",
    "drain_capacity": 50,
    "imperviousness": 0.974,
    "area": 10000.0,
    "elevation": "High-Density"
  },
  "902": {
    "ward_no": "263",
    "drain_capacity": 60,
    "imperviousness": 0.934,
    "area": 10000.0,
    "elevation": "Sink"
  },
  "554": {
    "ward_no": "264",
    "drain_capacity": 82,
    "imperviousness": 0.978,
    "area": 10000.0,
    "elevation": "High-Density"
  },
  "370": {
    "ward_no": "265",
    "drain_capacity": 111,
    "imperviousness": 0.98,
    "area": 10000.0,
    "elevation": "High-Density"
  },
  "678": {
    "ward_no": "268",
    "drain_capacity": 112,
    "imperviousness": 0.98,
    "area": 10000.0,
    "elevation": "Moderate"
  },
  "967": {
    "ward_no": "221",
    "drain_capacity": 148,
    "imperviousness": 0.948,
    "area": 10000.0,
    "elevation": "High-Density"
  },
  "17": {
    "ward_no": "271",
    "drain_capacity": 112,
    "imperviousness": 0.967,
    "area": 10000.0,
    "elevation": "High-Density"
  },
  "317": {
    "ward_no": "272",
    "drain_capacity": 111,
    "imperviousness": 0.98,
    "area": 10000.0,
    "elevation": "Low"
  },
  "308": {
    "ward_no": "154",
    "drain_capacity": 114,
    "imperviousness": 0.914,
    "area": 10000.0,
    "elevation": "Low"
  },
  "135": {
    "ward_no": "52",
    "drain_capacity": 73,
    "imperviousness": 0.91,
    "area": 10000.0,
    "elevation": "Low"
  },
  "812": {
    "ward_no": "157",
    "drain_capacity": 50,
    "imperviousness": 0.98,
    "area": 10000.0,
    "elevation": "High-Density"
  },
  "219": {
    "ward_no": "160",
    "drain_capacity": 62,
    "imperviousness": 0.893,
    "area": 10000.0,
    "elevation": "High-Density"
  },
  "369": {
    "ward_no": "161",
    "drain_capacity": 148,
    "imperviousness": 0.971,
    "area": 10000.0,
    "elevation": "High-Density"
  },
  "773": {
    "ward_no": "162",
    "drain_capacity": 56,
    "imperviousness": 0.957,
    "area": 10000.0,
    "elevation": "Moderate"
  },
  "106": {
    "ward_no": "159",
    "drain_capacity": 55,
    "imperviousness": 0.909,
    "area": 10000.0,
    "elevation": "Sink"
  },
  "165": {
    "ward_no": "170",
    "drain_capacity": 112,
    "imperviousness": 0.98,
    "area": 10000.0,
    "elevation": "High-Density"
  },
  "911": {
    "ward_no": "131",
    "drain_capacity": 50,
    "imperviousness": 0.963,
    "area": 10000.0,
    "elevation": "Moderate"
  },
  "284": {
    "ward_no": "168",
    "drain_capacity": 50,
    "imperviousness": 0.948,
    "area": 10000.0,
    "elevation": "High-Density"
  },
  "255": {
    "ward_no": "171",
    "drain_capacity": 50,
    "imperviousness": 0.974,
    "area": 10000.0,
    "elevation": "Sink"
  },
  "521": {
    "ward_no": "180",
    "drain_capacity": 93,
    "imperviousness": 0.98,
    "area": 10000.0,
    "elevation": "Sink"
  },
  "790": {
    "ward_no": "181",
    "drain_capacity": 57,
    "imperviousness": 0.874,
    "area": 10000.0,
    "elevation": "Sink"
  },
  "488": {
    "ward_no": "182",
    "drain_capacity": 53,
    "imperviousness": 0.924,
    "area": 10000.0,
    "elevation": "High-Density"
  },
  "577": {
    "ward_no": "147",
    "drain_capacity": 112,
    "imperviousness": 0.905,
    "area": 10000.0,
    "elevation": "Low"
  },
  "414": {
    "ward_no": "21",
    "drain_capacity": 96,
    "imperviousness": 0.936,
    "area": 10000.0,
    "elevation": "Sink"
  },
  "648": {
    "ward_no": "185",
    "drain_capacity": 102,
    "imperviousness": 0.893,
    "area": 10000.0,
    "elevation": "Sink"
  },
  "668": {
    "ward_no": "187",
    "drain_capacity": 143,
    "imperviousness": 0.98,
    "area": 10000.0,
    "elevation": "High-Density"
  },
  "585": {
    "ward_no": "169",
    "drain_capacity": 50,
    "imperviousness": 0.98,
    "area": 10000.0,
    "elevation": "Sink"
  },
  "436": {
    "ward_no": "189",
    "drain_capacity": 115,
    "imperviousness": 0.963,
    "area": 10000.0,
    "elevation": "Sink"
  },
  "613": {
    "ward_no": "190",
    "drain_capacity": 125,
    "imperviousness": 0.98,
    "area": 10000.0,
    "elevation": "High-Density"
  },
  "422": {
    "ward_no": "235",
    "drain_capacity": 89,
    "imperviousness": 0.98,
    "area": 10000.0,
    "elevation": "High-Density"
  },
  "356": {
    "ward_no": "192",
    "drain_capacity": 84,
    "imperviousness": 0.98,
    "area": 10000.0,
    "elevation": "Moderate"
  },
  "163": {
    "ward_no": "27",
    "drain_capacity": 99,
    "imperviousness": 0.98,
    "area": 10000.0,
    "elevation": "Low"
  },
  "373": {
    "ward_no": "194",
    "drain_capacity": 215,
    "imperviousness": 0.857,
    "area": 10000.0,
    "elevation": "Low"
  },
  "838": {
    "ward_no": "195",
    "drain_capacity": 79,
    "imperviousness": 0.954,
    "area": 10000.0,
    "elevation": "Low"
  },
  "280": {
    "ward_no": "196",
    "drain_capacity": 76,
    "imperviousness": 0.98,
    "area": 10000.0,
    "elevation": "Low"
  },
  "765": {
    "ward_no": "197",
    "drain_capacity": 178,
    "imperviousness": 0.956,
    "area": 10000.0,
    "elevation": "Low"
  },
  "602": {
    "ward_no": "198",
    "drain_capacity": 63,
    "imperviousness": 0.961,
    "area": 10000.0,
    "elevation": "Low"
  },
  "339": {
    "ward_no": "199",
    "drain_capacity": 219,
    "imperviousness": 0.98,
    "area": 10000.0,
    "elevation": "High-Density"
  },
  "659": {
    "ward_no": "200",
    "drain_capacity": 50,
    "imperviousness": 0.959,
    "area": 10000.0,
    "elevation": "High-Density"
  },
  "152": {
    "ward_no": "111",
    "drain_capacity": 226,
    "imperviousness": 0.976,
    "area": 10000.0,
    "elevation": "Moderate"
  },
  "342": {
    "ward_no": "217",
    "drain_capacity": 153,
    "imperviousness": 0.98,
    "area": 10000.0,
    "elevation": "Moderate"
  },
  "986": {
    "ward_no": "203",
    "drain_capacity": 83,
    "imperviousness": 0.934,
    "area": 10000.0,
    "elevation": "Low"
  },
  "968": {
    "ward_no": "204",
    "drain_capacity": 188,
    "imperviousness": 0.97,
    "area": 10000.0,
    "elevation": "High-Density"
  },
  "795": {
    "ward_no": "206",
    "drain_capacity": 118,
    "imperviousness": 0.98,
    "area": 10000.0,
    "elevation": "High-Density"
  },
  "825": {
    "ward_no": "179",
    "drain_capacity": 50,
    "imperviousness": 0.886,
    "area": 10000.0,
    "elevation": "High-Density"
  },
  "382": {
    "ward_no": "86",
    "drain_capacity": 88,
    "imperviousness": 0.98,
    "area": 10000.0,
    "elevation": "Low"
  },
  "311": {
    "ward_no": "87",
    "drain_capacity": 50,
    "imperviousness": 0.899,
    "area": 10000.0,
    "elevation": "Low"
  },
  "658": {
    "ward_no": "88",
    "drain_capacity": 50,
    "imperviousness": 0.885,
    "area": 10000.0,
    "elevation": "High-Density"
  },
  "306": {
    "ward_no": "89",
    "drain_capacity": 77,
    "imperviousness": 0.957,
    "area": 10000.0,
    "elevation": "Moderate"
  },
  "457": {
    "ward_no": "146",
    "drain_capacity": 102,
    "imperviousness": 0.98,
    "area": 10000.0,
    "elevation": "Sink"
  },
  "581": {
    "ward_no": "150",
    "drain_capacity": 50,
    "imperviousness": 0.973,
    "area": 10000.0,
    "elevation": "Low"
  },
  "939": {
    "ward_no": "61",
    "drain_capacity": 144,
    "imperviousness": 0.943,
    "area": 10000.0,
    "elevation": "Moderate"
  },
  "520": {
    "ward_no": "37",
    "drain_capacity": 90,
    "imperviousness": 0.948,
    "area": 10000.0,
    "elevation": "Moderate"
  },
  "406": {
    "ward_no": "173",
    "drain_capacity": 69,
    "imperviousness": 0.98,
    "area": 10000.0,
    "elevation": "High-Density"
  },
  "607": {
    "ward_no": "174",
    "drain_capacity": 92,
    "imperviousness": 0.979,
    "area": 10000.0,
    "elevation": "Sink"
  },
  "791": {
    "ward_no": "231",
    "drain_capacity": 127,
    "imperviousness": 0.914,
    "area": 10000.0,
    "elevation": "Sink"
  },
  "162": {
    "ward_no": "176",
    "drain_capacity": 70,
    "imperviousness": 0.98,
    "area": 10000.0,
    "elevation": "Low"
  },
  "417": {
    "ward_no": "208",
    "drain_capacity": 140,
    "imperviousness": 0.98,
    "area": 10000.0,
    "elevation": "Low"
  },
  "876": {
    "ward_no": "232",
    "drain_capacity": 98,
    "imperviousness": 0.956,
    "area": 10000.0,
    "elevation": "Moderate"
  },
  "7": {
    "ward_no": "234",
    "drain_capacity": 66,
    "imperviousness": 0.98,
    "area": 10000.0,
    "elevation": "Sink"
  },
  "196": {
    "ward_no": "78",
    "drain_capacity": 116,
    "imperviousness": 0.909,
    "area": 10000.0,
    "elevation": "High-Density"
  },
  "185": {
    "ward_no": "138",
    "drain_capacity": 69,
    "imperviousness": 0.88,
    "area": 10000.0,
    "elevation": "Low"
  },
  "819": {
    "ward_no": "238",
    "drain_capacity": 88,
    "imperviousness": 0.98,
    "area": 10000.0,
    "elevation": "Low"
  },
  "835": {
    "ward_no": "239",
    "drain_capacity": 116,
    "imperviousness": 0.943,
    "area": 10000.0,
    "elevation": "Sink"
  },
  "428": {
    "ward_no": "240",
    "drain_capacity": 195,
    "imperviousness": 0.98,
    "area": 10000.0,
    "elevation": "Moderate"
  },
  "93": {
    "ward_no": "148",
    "drain_capacity": 142,
    "imperviousness": 0.834,
    "area": 10000.0,
    "elevation": "Sink"
  },
  "872": {
    "ward_no": "96",
    "drain_capacity": 138,
    "imperviousness": 0.98,
    "area": 10000.0,
    "elevation": "High-Density"
  },
  "96": {
    "ward_no": "97",
    "drain_capacity": 99,
    "imperviousness": 0.905,
    "area": 10000.0,
    "elevation": "Low"
  },
  "104": {
    "ward_no": "98",
    "drain_capacity": 50,
    "imperviousness": 0.98,
    "area": 10000.0,
    "elevation": "Sink"
  },
  "722": {
    "ward_no": "122",
    "drain_capacity": 58,
    "imperviousness": 0.934,
    "area": 10000.0,
    "elevation": "Low"
  },
  "580": {
    "ward_no": "71",
    "drain_capacity": 130,
    "imperviousness": 0.98,
    "area": 10000.0,
    "elevation": "Low"
  },
  "87": {
    "ward_no": "72",
    "drain_capacity": 112,
    "imperviousness": 0.925,
    "area": 10000.0,
    "elevation": "Low"
  },
  "300": {
    "ward_no": "69",
    "drain_capacity": 127,
    "imperviousness": 0.98,
    "area": 10000.0,
    "elevation": "Low"
  },
  "378": {
    "ward_no": "74",
    "drain_capacity": 50,
    "imperviousness": 0.88,
    "area": 10000.0,
    "elevation": "Sink"
  },
  "341": {
    "ward_no": "75",
    "drain_capacity": 66,
    "imperviousness": 0.98,
    "area": 10000.0,
    "elevation": "Low"
  },
  "220": {
    "ward_no": "76",
    "drain_capacity": 115,
    "imperviousness": 0.98,
    "area": 10000.0,
    "elevation": "Moderate"
  },
  "814": {
    "ward_no": "77",
    "drain_capacity": 84,
    "imperviousness": 0.95,
    "area": 10000.0,
    "elevation": "Moderate"
  },
  "855": {
    "ward_no": "79",
    "drain_capacity": 124,
    "imperviousness": 0.954,
    "area": 10000.0,
    "elevation": "Moderate"
  },
  "469": {
    "ward_no": "114",
    "drain_capacity": 134,
    "imperviousness": 0.93,
    "area": 10000.0,
    "elevation": "Low"
  },
  "331": {
    "ward_no": "115",
    "drain_capacity": 103,
    "imperviousness": 0.98,
    "area": 10000.0,
    "elevation": "Sink"
  },
  "321": {
    "ward_no": "116",
    "drain_capacity": 104,
    "imperviousness": 0.911,
    "area": 10000.0,
    "elevation": "Sink"
  },
  "144": {
    "ward_no": "125",
    "drain_capacity": 213,
    "imperviousness": 0.97,
    "area": 10000.0,
    "elevation": "High-Density"
  },
  "362": {
    "ward_no": "126",
    "drain_capacity": 207,
    "imperviousness": 0.912,
    "area": 10000.0,
    "elevation": "High-Density"
  },
  "349": {
    "ward_no": "127",
    "drain_capacity": 94,
    "imperviousness": 0.98,
    "area": 10000.0,
    "elevation": "High-Density"
  },
  "394": {
    "ward_no": "143",
    "drain_capacity": 78,
    "imperviousness": 0.922,
    "area": 10000.0,
    "elevation": "High-Density"
  },
  "930": {
    "ward_no": "136",
    "drain_capacity": 117,
    "imperviousness": 0.98,
    "area": 10000.0,
    "elevation": "Moderate"
  },
  "985": {
    "ward_no": "137",
    "drain_capacity": 128,
    "imperviousness": 0.98,
    "area": 10000.0,
    "elevation": "Low"
  },
  "385": {
    "ward_no": "209",
    "drain_capacity": 50,
    "imperviousness": 0.98,
    "area": 10000.0,
    "elevation": "Sink"
  },
  "387": {
    "ward_no": "210",
    "drain_capacity": 50,
    "imperviousness": 0.98,
    "area": 10000.0,
    "elevation": "Sink"
  },
  "500": {
    "ward_no": "211",
    "drain_capacity": 113,
    "imperviousness": 0.964,
    "area": 10000.0,
    "elevation": "Moderate"
  },
  "552": {
    "ward_no": "212",
    "drain_capacity": 50,
    "imperviousness": 0.92,
    "area": 10000.0,
    "elevation": "Low"
  },
  "548": {
    "ward_no": "213",
    "drain_capacity": 112,
    "imperviousness": 0.965,
    "area": 10000.0,
    "elevation": "Sink"
  },
  "81": {
    "ward_no": "214",
    "drain_capacity": 100,
    "imperviousness": 0.952,
    "area": 10000.0,
    "elevation": "High-Density"
  },
  "748": {
    "ward_no": "215",
    "drain_capacity": 84,
    "imperviousness": 0.87,
    "area": 10000.0,
    "elevation": "Low"
  },
  "545": {
    "ward_no": "216",
    "drain_capacity": 106,
    "imperviousness": 0.976,
    "area": 10000.0,
    "elevation": "Low"
  },
  "528": {
    "ward_no": "68",
    "drain_capacity": 116,
    "imperviousness": 0.913,
    "area": 10000.0,
    "elevation": "High-Density"
  },
  "285": {
    "ward_no": "91",
    "drain_capacity": 124,
    "imperviousness": 0.98,
    "area": 10000.0,
    "elevation": "Sink"
  },
  "612": {
    "ward_no": "66",
    "drain_capacity": 203,
    "imperviousness": 0.98,
    "area": 10000.0,
    "elevation": "Sink"
  },
  "6": {
    "ward_no": "65",
    "drain_capacity": 50,
    "imperviousness": 0.937,
    "area": 10000.0,
    "elevation": "Low"
  },
  "942": {
    "ward_no": "64",
    "drain_capacity": 132,
    "imperviousness": 0.98,
    "area": 10000.0,
    "elevation": "High-Density"
  },
  "729": {
    "ward_no": "63",
    "drain_capacity": 78,
    "imperviousness": 0.933,
    "area": 10000.0,
    "elevation": "Low"
  },
  "304": {
    "ward_no": "62",
    "drain_capacity": 152,
    "imperviousness": 0.862,
    "area": 10000.0,
    "elevation": "Moderate"
  },
  "987": {
    "ward_no": "60",
    "drain_capacity": 175,
    "imperviousness": 0.954,
    "area": 10000.0,
    "elevation": "Moderate"
  },
  "167": {
    "ward_no": "59",
    "drain_capacity": 149,
    "imperviousness": 0.967,
    "area": 10000.0,
    "elevation": "Sink"
  },
  "922": {
    "ward_no": "58",
    "drain_capacity": 50,
    "imperviousness": 0.947,
    "area": 10000.0,
    "elevation": "Moderate"
  },
  "265": {
    "ward_no": "57",
    "drain_capacity": 99,
    "imperviousness": 0.97,
    "area": 10000.0,
    "elevation": "Moderate"
  },
  "988": {
    "ward_no": "56",
    "drain_capacity": 50,
    "imperviousness": 0.98,
    "area": 10000.0,
    "elevation": "Low"
  },
  "645": {
    "ward_no": "55",
    "drain_capacity": 50,
    "imperviousness": 0.974,
    "area": 10000.0,
    "elevation": "Moderate"
  },
  "553": {
    "ward_no": "54",
    "drain_capacity": 96,
    "imperviousness": 0.98,
    "area": 10000.0,
    "elevation": "High-Density"
  },
  "160": {
    "ward_no": "35",
    "drain_capacity": 67,
    "imperviousness": 0.896,
    "area": 10000.0,
    "elevation": "Low"
  },
  "426": {
    "ward_no": "51",
    "drain_capacity": 50,
    "imperviousness": 0.94,
    "area": 10000.0,
    "elevation": "Moderate"
  },
  "946": {
    "ward_no": "50",
    "drain_capacity": 198,
    "imperviousness": 0.952,
    "area": 10000.0,
    "elevation": "Low"
  },
  "639": {
    "ward_no": "48",
    "drain_capacity": 125,
    "imperviousness": 0.98,
    "area": 10000.0,
    "elevation": "Low"
  },
  "622": {
    "ward_no": "46",
    "drain_capacity": 94,
    "imperviousness": 0.939,
    "area": 10000.0,
    "elevation": "Sink"
  },
  "873": {
    "ward_no": "44",
    "drain_capacity": 86,
    "imperviousness": 0.835,
    "area": 10000.0,
    "elevation": "High-Density"
  },
  "210": {
    "ward_no": "43",
    "drain_capacity": 68,
    "imperviousness": 0.84,
    "area": 10000.0,
    "elevation": "High-Density"
  },
  "84": {
    "ward_no": "42",
    "drain_capacity": 128,
    "imperviousness": 0.966,
    "area": 10000.0,
    "elevation": "High-Density"
  },
  "517": {
    "ward_no": "41",
    "drain_capacity": 51,
    "imperviousness": 0.954,
    "area": 10000.0,
    "elevation": "Moderate"
  },
  "544": {
    "ward_no": "40",
    "drain_capacity": 50,
    "imperviousness": 0.96,
    "area": 10000.0,
    "elevation": "Low"
  },
  "256": {
    "ward_no": "8",
    "drain_capacity": 144,
    "imperviousness": 0.955,
    "area": 10000.0,
    "elevation": "High-Density"
  },
  "257": {
    "ward_no": "25",
    "drain_capacity": 218,
    "imperviousness": 0.98,
    "area": 10000.0,
    "elevation": "High-Density"
  },
  "400": {
    "ward_no": "24",
    "drain_capacity": 50,
    "imperviousness": 0.94,
    "area": 10000.0,
    "elevation": "Low"
  },
  "361": {
    "ward_no": "230",
    "drain_capacity": 169,
    "imperviousness": 0.885,
    "area": 10000.0,
    "elevation": "High-Density"
  },
  "158": {
    "ward_no": "229",
    "drain_capacity": 50,
    "imperviousness": 0.978,
    "area": 10000.0,
    "elevation": "Low"
  },
  "132": {
    "ward_no": "228",
    "drain_capacity": 77,
    "imperviousness": 0.919,
    "area": 10000.0,
    "elevation": "Low"
  },
  "950": {
    "ward_no": "30",
    "drain_capacity": 69,
    "imperviousness": 0.98,
    "area": 10000.0,
    "elevation": "High-Density"
  },
  "353": {
    "ward_no": "225",
    "drain_capacity": 50,
    "imperviousness": 0.98,
    "area": 10000.0,
    "elevation": "Sink"
  },
  "62": {
    "ward_no": "223",
    "drain_capacity": 88,
    "imperviousness": 0.905,
    "area": 10000.0,
    "elevation": "Sink"
  },
  "179": {
    "ward_no": "222",
    "drain_capacity": 111,
    "imperviousness": 0.964,
    "area": 10000.0,
    "elevation": "Low"
  },
  "166": {
    "ward_no": "22",
    "drain_capacity": 125,
    "imperviousness": 0.901,
    "area": 10000.0,
    "elevation": "Sink"
  },
  "583": {
    "ward_no": "219",
    "drain_capacity": 202,
    "imperviousness": 0.98,
    "area": 10000.0,
    "elevation": "Low"
  },
  "534": {
    "ward_no": "218",
    "drain_capacity": 66,
    "imperviousness": 0.979,
    "area": 10000.0,
    "elevation": "Moderate"
  },
  "640": {
    "ward_no": "100",
    "drain_capacity": 113,
    "imperviousness": 0.813,
    "area": 10000.0,
    "elevation": "Low"
  },
  "727": {
    "ward_no": "132",
    "drain_capacity": 67,
    "imperviousness": 0.952,
    "area": 10000.0,
    "elevation": "Moderate"
  },
  "498": {
    "ward_no": "95",
    "drain_capacity": 126,
    "imperviousness": 0.98,
    "area": 10000.0,
    "elevation": "Moderate"
  },
  "549": {
    "ward_no": "94",
    "drain_capacity": 50,
    "imperviousness": 0.898,
    "area": 10000.0,
    "elevation": "Sink"
  },
  "540": {
    "ward_no": "90",
    "drain_capacity": 116,
    "imperviousness": 0.929,
    "area": 10000.0,
    "elevation": "Low"
  },
  "289": {
    "ward_no": "70",
    "drain_capacity": 84,
    "imperviousness": 0.934,
    "area": 10000.0,
    "elevation": "Sink"
  },
  "551": {
    "ward_no": "4",
    "drain_capacity": 114,
    "imperviousness": 0.98,
    "area": 10000.0,
    "elevation": "Moderate"
  },
  "788": {
    "ward_no": "3",
    "drain_capacity": 86,
    "imperviousness": 0.98,
    "area": 10000.0,
    "elevation": "Sink"
  },
  "824": {
    "ward_no": "26",
    "drain_capacity": 50,
    "imperviousness": 0.9,
    "area": 10000.0,
    "elevation": "Moderate"
  },
  "286": {
    "ward_no": "2",
    "drain_capacity": 152,
    "imperviousness": 0.908,
    "area": 10000.0,
    "elevation": "High-Density"
  },
  "699": {
    "ward_no": "9",
    "drain_capacity": 116,
    "imperviousness": 0.939,
    "area": 10000.0,
    "elevation": "Moderate"
  },
  "916": {
    "ward_no": "6",
    "drain_capacity": 50,
    "imperviousness": 0.98,
    "area": 10000.0,
    "elevation": "Low"
  },
  "562": {
    "ward_no": "28",
    "drain_capacity": 125,
    "imperviousness": 0.98,
    "area": 10000.0,
    "elevation": "High-Density"
  },
  "90": {
    "ward_no": "19",
    "drain_capacity": 109,
    "imperviousness": 0.962,
    "area": 10000.0,
    "elevation": "Low"
  },
  "924": {
    "ward_no": "17",
    "drain_capacity": 50,
    "imperviousness": 0.909,
    "area": 10000.0,
    "elevation": "High-Density"
  },
  "288": {
    "ward_no": "16",
    "drain_capacity": 103,
    "imperviousness": 0.926,
    "area": 10000.0,
    "elevation": "High-Density"
  },
  "903": {
    "ward_no": "144",
    "drain_capacity": 86,
    "imperviousness": 0.901,
    "area": 10000.0,
    "elevation": "High-Density"
  },
  "397": {
    "ward_no": "141",
    "drain_capacity": 143,
    "imperviousness": 0.98,
    "area": 10000.0,
    "elevation": "High-Density"
  },
  "464": {
    "ward_no": "14",
    "drain_capacity": 50,
    "imperviousness": 0.964,
    "area": 10000.0,
    "elevation": "Moderate"
  },
  "478": {
    "ward_no": "13",
    "drain_capacity": 50,
    "imperviousness": 0.98,
    "area": 10000.0,
    "elevation": "Moderate"
  },
  "601": {
    "ward_no": "12",
    "drain_capacity": 109,
    "imperviousness": 0.98,
    "area": 10000.0,
    "elevation": "High-Density"
  },
  "451": {
    "ward_no": "10",
    "drain_capacity": 105,
    "imperviousness": 0.98,
    "area": 10000.0,
    "elevation": "High-Density"
  },
  "670": {
    "ward_no": "101",
    "drain_capacity": 110,
    "imperviousness": 0.972,
    "area": 10000.0,
    "elevation": "Low"
  },
  "411": {
    "ward_no": "102",
    "drain_capacity": 194,
    "imperviousness": 0.98,
    "area": 10000.0,
    "elevation": "Moderate"
  },
  "828": {
    "ward_no": "105",
    "drain_capacity": 109,
    "imperviousness": 0.955,
    "area": 10000.0,
    "elevation": "Sink"
  },
  "392": {
    "ward_no": "110",
    "drain_capacity": 50,
    "imperviousness": 0.944,
    "area": 10000.0,
    "elevation": "Sink"
  },
  "303": {
    "ward_no": "112",
    "drain_capacity": 92,
    "imperviousness": 0.929,
    "area": 10000.0,
    "elevation": "Sink"
  },
  "547": {
    "ward_no": "23",
    "drain_capacity": 50,
    "imperviousness": 0.885,
    "area": 10000.0,
    "elevation": "High-Density"
  },
  "262": {
    "ward_no": "31",
    "drain_capacity": 50,
    "imperviousness": 0.937,
    "area": 10000.0,
    "elevation": "Moderate"
  },
  "97": {
    "ward_no": "34",
    "drain_capacity": 87,
    "imperviousness": 0.936,
    "area": 10000.0,
    "elevation": "Moderate"
  },
  "742": {
    "ward_no": "39",
    "drain_capacity": 140,
    "imperviousness": 0.942,
    "area": 10000.0,
    "elevation": "Moderate"
  },
  "128": {
    "ward_no": "49",
    "drain_capacity": 192,
    "imperviousness": 0.98,
    "area": 10000.0,
    "elevation": "Low"
  },
  "259": {
    "ward_no": "18",
    "drain_capacity": 50,
    "imperviousness": 0.976,
    "area": 10000.0,
    "elevation": "Sink"
  },
  "687": {
    "ward_no": "254",
    "drain_capacity": 86,
    "imperviousness": 0.895,
    "area": 10000.0,
    "elevation": "Low"
  },
  "720": {
    "ward_no": "142",
    "drain_capacity": 121,
    "imperviousness": 0.96,
    "area": 10000.0,
    "elevation": "Low"
  },
  "299": {
    "ward_no": "99",
    "drain_capacity": 100,
    "imperviousness": 0.949,
    "area": 10000.0,
    "elevation": "Low"
  },
  "877": {
    "ward_no": "155",
    "drain_capacity": 98,
    "imperviousness": 0.923,
    "area": 10000.0,
    "elevation": "High-Density"
  },
  "107": {
    "ward_no": "145",
    "drain_capacity": 169,
    "imperviousness": 0.817,
    "area": 10000.0,
    "elevation": "Moderate"
  },
  "781": {
    "ward_no": "226",
    "drain_capacity": 114,
    "imperviousness": 0.937,
    "area": 10000.0,
    "elevation": "Sink"
  },
  "237": {
    "ward_no": "104",
    "drain_capacity": 50,
    "imperviousness": 0.911,
    "area": 10000.0,
    "elevation": "High-Density"
  },
  "962": {
    "ward_no": "149",
    "drain_capacity": 81,
    "imperviousness": 0.947,
    "area": 10000.0,
    "elevation": "Low"
  },
  "22": {
    "ward_no": "167",
    "drain_capacity": 146,
    "imperviousness": 0.98,
    "area": 10000.0,
    "elevation": "Low"
  },
  "366": {
    "ward_no": "163",
    "drain_capacity": 64,
    "imperviousness": 0.914,
    "area": 10000.0,
    "elevation": "High-Density"
  },
  "14": {
    "ward_no": "164",
    "drain_capacity": 73,
    "imperviousness": 0.974,
    "area": 10000.0,
    "elevation": "High-Density"
  },
  "227": {
    "ward_no": "130",
    "drain_capacity": 135,
    "imperviousness": 0.972,
    "area": 10000.0,
    "elevation": "Sink"
  },
  "883": {
    "ward_no": "38",
    "drain_capacity": 182,
    "imperviousness": 0.9,
    "area": 10000.0,
    "elevation": "Low"
  },
  "463": {
    "ward_no": "106",
    "drain_capacity": 129,
    "imperviousness": 0.935,
    "area": 10000.0,
    "elevation": "Low"
  },
  "589": {
    "ward_no": "1",
    "drain_capacity": 73,
    "imperviousness": 0.98,
    "area": 10000.0,
    "elevation": "Low"
  },
  "801": {
    "ward_no": "5",
    "drain_capacity": 165,
    "imperviousness": 0.862,
    "area": 10000.0,
    "elevation": "Low"
  },
  "754": {
    "ward_no": "7",
    "drain_capacity": 50,
    "imperviousness": 0.98,
    "area": 10000.0,
    "elevation": "High-Density"
  },
  "755": {
    "ward_no": "220",
    "drain_capacity": 50,
    "imperviousness": 0.923,
    "area": 10000.0,
    "elevation": "Sink"
  },
  "2": {
    "ward_no": "224",
    "drain_capacity": 72,
    "imperviousness": 0.97,
    "area": 10000.0,
    "elevation": "Sink"
  },
  "657": {
    "ward_no": "233",
    "drain_capacity": 81,
    "imperviousness": 0.947,
    "area": 10000.0,
    "elevation": "Low"
  },
  "646": {
    "ward_no": "251",
    "drain_capacity": 207,
    "imperviousness": 0.98,
    "area": 10000.0,
    "elevation": "Low"
  },
  "446": {
    "ward_no": "253",
    "drain_capacity": 108,
    "imperviousness": 0.941,
    "area": 10000.0,
    "elevation": "Sink"
  },
  "89": {
    "ward_no": "267",
    "drain_capacity": 50,
    "imperviousness": 0.955,
    "area": 10000.0,
    "elevation": "Low"
  },
  "122": {
    "ward_no": "177",
    "drain_capacity": 109,
    "imperviousness": 0.901,
    "area": 10000.0,
    "elevation": "Low"
  },
  "980": {
    "ward_no": "178",
    "drain_capacity": 200,
    "imperviousness": 0.98,
    "area": 10000.0,
    "elevation": "Sink"
  },
  "83": {
    "ward_no": "186",
    "drain_capacity": 50,
    "imperviousness": 0.976,
    "area": 10000.0,
    "elevation": "Sink"
  },
  "990": {
    "ward_no": "205",
    "drain_capacity": 82,
    "imperviousness": 0.96,
    "area": 10000.0,
    "elevation": "High-Density"
  },
  "172": {
    "ward_no": "20",
    "drain_capacity": 167,
    "imperviousness": 0.906,
    "area": 10000.0,
    "elevation": "Low"
  },
  "278": {
    "ward_no": "121",
    "drain_capacity": 52,
    "imperviousness": 0.98,
    "area": 10000.0,
    "elevation": "High-Density"
  },
  "433": {
    "ward_no": "124",
    "drain_capacity": 104,
    "imperviousness": 0.959,
    "area": 10000.0,
    "elevation": "Low"
  },
  "627": {
    "ward_no": "123",
    "drain_capacity": 71,
    "imperviousness": 0.956,
    "area": 10000.0,
    "elevation": "Moderate"
  },
  "894": {
    "ward_no": "153",
    "drain_capacity": 98,
    "imperviousness": 0.98,
    "area": 10000.0,
    "elevation": "High-Density"
  },
  "313": {
    "ward_no": "93",
    "drain_capacity": 50,
    "imperviousness": 0.93,
    "area": 10000.0,
    "elevation": "Sink"
  },
  "767": {
    "ward_no": "32",
    "drain_capacity": 131,
    "imperviousness": 0.98,
    "area": 10000.0,
    "elevation": "Low"
  },
  "784": {
    "ward_no": "36",
    "drain_capacity": 50,
    "imperviousness": 0.98,
    "area": 10000.0,
    "elevation": "Low"
  },
  "744": {
    "ward_no": "33",
    "drain_capacity": 96,
    "imperviousness": 0.98,
    "area": 10000.0,
    "elevation": "Low"
  },
  "138": {
    "ward_no": "73",
    "drain_capacity": 153,
    "imperviousness": 0.956,
    "area": 10000.0,
    "elevation": "High-Density"
  },
  "809": {
    "ward_no": "107",
    "drain_capacity": 127,
    "imperviousness": 0.98,
    "area": 10000.0,
    "elevation": "High-Density"
  },
  "168": {
    "ward_no": "270",
    "drain_capacity": 77,
    "imperviousness": 0.98,
    "area": 10000.0,
    "elevation": "Moderate"
  }
}